snyp.py
snyp-0.1.3.dist-info/LICENSE
snyp-0.1.3.dist-info/METADATA
snyp-0.1.3.dist-info/WHEEL
snyp-0.1.3.dist-info/entry_points.txt
snyp-0.1.3.dist-info/top_level.txt
snyp-0.1.3.dist-info/RECORD
