Metadata-Version: 2.1
Name: snyp
Version: 0.1.3
Summary: Snyp is a command line utility that streamlines the process of creating text based documentation and programming tutorials in Markdown.
Home-page: https://github.com/BujarMurati/snyp
Author: Bujar Murati
Author-email: bmurati95@gmail.com
License: UNKNOWN
Platform: UNKNOWN
Classifier: Programming Language :: Python :: 3
Classifier: License :: OSI Approved :: MIT License
Classifier: Operating System :: OS Independent
Requires-Dist: Click
Requires-Dist: configparser
